{
  "project_info": {
    "project_number": "1004737641004",
    "firebase_url": "https://babynamespoll.firebaseio.com",
    "project_id": "babynamespoll",
    "storage_bucket": "babynamespoll.appspot.com"
  },
  "client": [
    {
      "client_info": {
        "mobilesdk_app_id": "1:1004737641004:android:92ed5431056d4e57",
        "android_client_info": {
          "package_name": "com.rayfocus.babynames"
        }
      },
      "oauth_client": [
        {
          "client_id": "1004737641004-96guvsf5tntcmdibdit32k1piaofodbt.apps.googleusercontent.com",
          "client_type": 3
        }
      ],
      "api_key": [
        {
          "current_key": "AIzaSyAjJFPu0pE36I_a2JROvx_bfCsWPJLBuAE"
        }
      ],
      "services": {
        "analytics_service": {
          "status": 1
        },
        "appinvite_service": {
          "status": 1,
          "other_platform_oauth_client": []
        },
        "ads_service": {
          "status": 2
        }
      }
    }
  ],
  "configuration_version": "1"
}